mybase/__init__.py
mybase/__init__.pyc
mybase/base.py
mybase/base.pyc
mybase/tests/__init__.py
mybase/tests/__main__.py
mybase/tests/helper.py
mybase/tests/test_base.py
mybase-0.1.1.dist-info/METADATA
mybase-0.1.1.dist-info/WHEEL
mybase-0.1.1.dist-info/top_level.txt
mybase-0.1.1.dist-info/zip-safe
mybase-0.1.1.dist-info/RECORD
